valopy/__init__.py
valopy/adapter.py
valopy/client.py
valopy/enums.py
valopy/exceptions.py
valopy/models.py
valopy/utils.py
valopy-0.4.1.dist-info/licenses/LICENSE
valopy-0.4.1.dist-info/METADATA
valopy-0.4.1.dist-info/WHEEL
valopy-0.4.1.dist-info/top_level.txt
valopy-0.4.1.dist-info/RECORD
