Metadata-Version: 2.4
Name: valopy
Version: 0.4.1
Summary: An async Python wrapper for the unofficial Valorant API.
Author: Vinc0739
Maintainer: Vinc0739
License: MIT
Project-URL: Documentation, https://valopy.readthedocs.io/
Project-URL: Bug Tracker, https://github.com/Vinc0739/valopy/issues
Project-URL: Source Code, https://github.com/Vinc0739/valopy
Keywords: valorant,api,async,wrapper,aiohttp,python,gaming,riot-games
Classifier: Development Status :: 4 - Beta
Classifier: Environment :: Plugins
Classifier: Intended Audience :: Developers
Classifier: License :: OSI Approved :: MIT License
Classifier: Natural Language :: English
Classifier: Operating System :: OS Independent
Classifier: Programming Language :: Python :: 3
Classifier: Programming Language :: Python :: 3.11
Classifier: Programming Language :: Python :: 3.12
Classifier: Programming Language :: Python :: 3.13
Classifier: Programming Language :: Python :: 3.14
Classifier: Topic :: Software Development :: Libraries :: Python Modules
Classifier: Topic :: Games/Entertainment :: First Person Shooters
Classifier: Typing :: Typed
Requires-Python: >=3.11
License-File: LICENSE
Requires-Dist: aiohttp>=3.13.3
Dynamic: license-file
